flatds/__init__.py
flatds-0.0.1.dist-info/LICENSE
flatds-0.0.1.dist-info/METADATA
flatds-0.0.1.dist-info/WHEEL
flatds-0.0.1.dist-info/top_level.txt
flatds-0.0.1.dist-info/RECORD
